[
  {
    "Title": "Mesaerion: The Best Science ...",
    "Price": "£37.59"
  },
  {
    "Title": "Join",
    "Price": "£35.67"
  },
  {
    "Title": "William Shakespeare's Star Wars: ...",
    "Price": "£43.30"
  },
  {
    "Title": "The Project",
    "Price": "£10.65"
  },
  {
    "Title": "Soft Apocalypse",
    "Price": "£26.12"
  },
  {
    "Title": "Sleeping Giants (Themis Files ...",
    "Price": "£48.74"
  },
  {
    "Title": "Arena",
    "Price": "£21.36"
  },
  {
    "Title": "Foundation (Foundation (Publication Order) ...",
    "Price": "£32.42"
  },
  {
    "Title": "The Restaurant at the ...",
    "Price": "£10.92"
  },
  {
    "Title": "Ready Player One",
    "Price": "£19.07"
  },
  {
    "Title": "Life, the Universe and ...",
    "Price": "£33.26"
  },
  {
    "Title": "Dune (Dune #1)",
    "Price": "£54.86"
  },
  {
    "Title": "Do Androids Dream of ...",
    "Price": "£51.48"
  },
  {
    "Title": "Three Wishes (River of ...",
    "Price": "£44.18"
  },
  {
    "Title": "The Last Girl (The ...",
    "Price": "£36.26"
  },
  {
    "Title": "Having the Barbarian's Baby ...",
    "Price": "£34.96"
  }
]